keyword_extract_links/extract_links.py
keyword_extract_links-0.0.4.dist-info/METADATA
keyword_extract_links-0.0.4.dist-info/WHEEL
keyword_extract_links-0.0.4.dist-info/top_level.txt
keyword_extract_links-0.0.4.dist-info/RECORD
