Metadata-Version: 2.1
Name: keyword-extract-links
Version: 0.0.4
Summary: This is a package that extracts keyword links based on web keywords
Home-page: https://github.com/lvyunze/keyword_extract_links
Author: lvyunze
Author-email: 17817462542@163.com
License: UNKNOWN
Keywords: extracts keyword links based on web keywords
Platform: UNKNOWN
Classifier: Programming Language :: Python :: 3
Classifier: License :: OSI Approved :: MIT License
Classifier: Operating System :: OS Independent
Requires-Python: >=3.6
Requires-Dist: lxml (==4.6.2)
